autocleaneeg_sl/__init__.py
autocleaneeg_sl/cli.py
autocleaneeg_sl/config.py
autocleaneeg_sl/core.py
autocleaneeg_sl/epoch.py
autocleaneeg_sl-0.2.0.dist-info/METADATA
autocleaneeg_sl-0.2.0.dist-info/WHEEL
autocleaneeg_sl-0.2.0.dist-info/entry_points.txt
autocleaneeg_sl-0.2.0.dist-info/licenses/LICENSE
autocleaneeg_sl-0.2.0.dist-info/RECORD
