Metadata-Version: 2.4
Name: autocleaneeg-sl
Version: 0.2.0
Summary: Statistical Learning analysis for EEG - Z-scored Inter-Trial Coherence (ZITC) computation
Project-URL: Homepage, https://github.com/cincibrainlab/autocleaneeg-sl
Project-URL: Repository, https://github.com/cincibrainlab/autocleaneeg-sl
Author: Cincinnati Brain Lab
License-Expression: MIT
License-File: LICENSE
Keywords: eeg,inter-trial-coherence,itc,neuroscience,signal-processing,statistical-learning
Classifier: Development Status :: 4 - Beta
Classifier: Intended Audience :: Science/Research
Classifier: License :: OSI Approved :: MIT License
Classifier: Programming Language :: Python :: 3
Classifier: Programming Language :: Python :: 3.9
Classifier: Programming Language :: Python :: 3.10
Classifier: Programming Language :: Python :: 3.11
Classifier: Programming Language :: Python :: 3.12
Classifier: Topic :: Scientific/Engineering
Requires-Python: >=3.9
Requires-Dist: mne>=1.0
Requires-Dist: numpy>=1.20
Requires-Dist: pandas>=1.3
Requires-Dist: pyyaml>=6.0
Provides-Extra: dev
Requires-Dist: eeglabio>=0.0.2; extra == 'dev'
Requires-Dist: pytest-cov>=4.0; extra == 'dev'
Requires-Dist: pytest>=7.0; extra == 'dev'
